pytorch_igniter/__init__.py
pytorch_igniter/args.py
pytorch_igniter/commands.py
pytorch_igniter/config.py
pytorch_igniter/copyxattr_patch.py
pytorch_igniter/engine.py
pytorch_igniter/evaluator.py
pytorch_igniter/events.py
pytorch_igniter/experiment_cli.py
pytorch_igniter/export.py
pytorch_igniter/hooks.py
pytorch_igniter/main.py
pytorch_igniter/metrics.py
pytorch_igniter/mlflow_ctx.py
pytorch_igniter/pipes.py
pytorch_igniter/spec.py
pytorch_igniter/ssm.py
pytorch_igniter/trainer.py
pytorch_igniter/util.py
pytorch_igniter/demo/__init__.py
pytorch_igniter/demo/mnist_model.py
pytorch_igniter/inference/__init__.py
pytorch_igniter/inference/audio_input_fn.py
pytorch_igniter/inference/greyscale_image_input_fn.py
pytorch_igniter/inference/image_input_fn.py
pytorch_igniter/inference/inference.py
pytorch_igniter/inference/json_output_fn.py
pytorch_igniter-0.0.47.dist-info/METADATA
pytorch_igniter-0.0.47.dist-info/WHEEL
pytorch_igniter-0.0.47.dist-info/top_level.txt
pytorch_igniter-0.0.47.dist-info/RECORD
