Metadata-Version: 2.1
Name: pytorch-igniter
Version: 0.0.47
Summary: Simplify running pytorch training with fully-configured pytorch-ignite
Home-page: https://github.com/bstriner/pytorch-igniter
Author: Ben Striner
Author-email: bstriner@gmail.com
License: UNKNOWN
Platform: UNKNOWN
Requires-Dist: pytorch-ignite
Requires-Dist: pyyaml
Requires-Dist: tqdm
Requires-Dist: mlflow
Requires-Dist: aws-sagemaker-remote
